blackmaria/__init__.py
blackmaria/cray.py
blackmaria/maria.py
blackmaria-0.1.dist-info/METADATA
blackmaria-0.1.dist-info/WHEEL
blackmaria-0.1.dist-info/top_level.txt
blackmaria-0.1.dist-info/RECORD
