Metadata-Version: 2.1
Name: blackmaria
Version: 0.1
Home-page: https://github.com/smyja/blackmaria
Author: Maro Akpobi
Author-email: akpobimaro@gmail.com
License: MIT
Requires-Dist: bs4
Requires-Dist: python-dotenv
Requires-Dist: guardrails-ai
Requires-Dist: gpt-index
